pyshell/commands/__init__.py
pyshell/commands/cat.py
pyshell/commands/cd.py
pyshell/commands/cp.py
pyshell/commands/find.py
pyshell/commands/grep.py
pyshell/commands/head.py
pyshell/commands/ls.py
pyshell/commands/mkdir.py
pyshell/commands/mv.py
pyshell/commands/pwd.py
pyshell/commands/rm.py
pyshell/commands/rmdir.py
pyshell/commands/sizeof.py
pyshell/commands/tail.py
pyshell_pybc2-0.4.0.dist-info/METADATA
pyshell_pybc2-0.4.0.dist-info/WHEEL
pyshell_pybc2-0.4.0.dist-info/top_level.txt
pyshell_pybc2-0.4.0.dist-info/RECORD
